odoo8_addon_hr_timesheet_activity_begin_end-8.0.1.0.0-py2.7-nspkg.pth
odoo8_addon_hr_timesheet_activity_begin_end-8.0.1.0.0.dist-info/top_level.txt
odoo8_addon_hr_timesheet_activity_begin_end-8.0.1.0.0.dist-info/WHEEL
odoo8_addon_hr_timesheet_activity_begin_end-8.0.1.0.0.dist-info/RECORD
odoo8_addon_hr_timesheet_activity_begin_end-8.0.1.0.0.dist-info/metadata.json
odoo8_addon_hr_timesheet_activity_begin_end-8.0.1.0.0.dist-info/DESCRIPTION.rst
odoo8_addon_hr_timesheet_activity_begin_end-8.0.1.0.0.dist-info/METADATA
odoo8_addon_hr_timesheet_activity_begin_end-8.0.1.0.0.dist-info/namespace_packages.txt
odoo_addons/hr_timesheet_activity_begin_end/__openerp__.py
odoo_addons/hr_timesheet_activity_begin_end/__init__.py
odoo_addons/hr_timesheet_activity_begin_end/README.rst
odoo_addons/hr_timesheet_activity_begin_end/models/account_analytic_line.py
odoo_addons/hr_timesheet_activity_begin_end/models/__init__.py
odoo_addons/hr_timesheet_activity_begin_end/i18n/hr_timesheet_activity_begin_end.pot
odoo_addons/hr_timesheet_activity_begin_end/i18n/fr.po
odoo_addons/hr_timesheet_activity_begin_end/views/hr_timesheet_sheet.xml
odoo_addons/hr_timesheet_activity_begin_end/views/hr_analytic_timesheet.xml
odoo_addons/hr_timesheet_activity_begin_end/tests/test_timesheet_begin_end.py
odoo_addons/hr_timesheet_activity_begin_end/tests/__init__.py
odoo_addons/hr_timesheet_activity_begin_end/static/description/icon.png
